odoo/addons/contract_line_successor/README.rst
odoo/addons/contract_line_successor/__init__.py
odoo/addons/contract_line_successor/__manifest__.py
odoo/addons/contract_line_successor/data/contract_renew_cron.xml
odoo/addons/contract_line_successor/i18n/contract_line_successor.pot
odoo/addons/contract_line_successor/i18n/fr.po
odoo/addons/contract_line_successor/i18n/it.po
odoo/addons/contract_line_successor/i18n/pt_BR.po
odoo/addons/contract_line_successor/i18n/sv.po
odoo/addons/contract_line_successor/i18n/tr.po
odoo/addons/contract_line_successor/models/__init__.py
odoo/addons/contract_line_successor/models/contract_contract.py
odoo/addons/contract_line_successor/models/contract_line.py
odoo/addons/contract_line_successor/models/contract_line_constraints.py
odoo/addons/contract_line_successor/models/contract_template.py
odoo/addons/contract_line_successor/models/contract_template_line.py
odoo/addons/contract_line_successor/models/res_company.py
odoo/addons/contract_line_successor/models/res_config_settings.py
odoo/addons/contract_line_successor/readme/CONFIGURE.md
odoo/addons/contract_line_successor/readme/CONTRIBUTORS.md
odoo/addons/contract_line_successor/readme/DESCRIPTION.md
odoo/addons/contract_line_successor/readme/USAGE.md
odoo/addons/contract_line_successor/security/ir.model.access.csv
odoo/addons/contract_line_successor/static/description/icon.png
odoo/addons/contract_line_successor/static/description/index.html
odoo/addons/contract_line_successor/tests/__init__.py
odoo/addons/contract_line_successor/tests/test_contract.py
odoo/addons/contract_line_successor/views/contract_contract.xml
odoo/addons/contract_line_successor/views/contract_line.xml
odoo/addons/contract_line_successor/views/contract_template.xml
odoo/addons/contract_line_successor/views/contract_template_line.xml
odoo/addons/contract_line_successor/views/res_config_settings.xml
odoo/addons/contract_line_successor/wizards/__init__.py
odoo_addon_contract_line_successor-18.0.1.0.1.9.dist-info/METADATA
odoo_addon_contract_line_successor-18.0.1.0.1.9.dist-info/WHEEL
odoo_addon_contract_line_successor-18.0.1.0.1.9.dist-info/top_level.txt
odoo_addon_contract_line_successor-18.0.1.0.1.9.dist-info/RECORD
